raiplaysound/__init__.py
raiplaysound/__main__.py
raiplaysound/all.py
raiplaysound/index.py
raiplaysound/index.template
raiplaysound/single.py
raiplaysound-0.7.0.dist-info/entry_points.txt
raiplaysound-0.7.0.dist-info/licenses/LICENSE
raiplaysound-0.7.0.dist-info/WHEEL
raiplaysound-0.7.0.dist-info/METADATA
raiplaysound-0.7.0.dist-info/RECORD
