Metadata-Version: 2.4
Name: raiplaysound
Version: 0.7.0
Summary: Podcast generator for RaiPlay Sound
Author: Timendum
Requires-Python: >=3.12
License-File: LICENSE
Requires-Dist: beautifulsoup4>=4.12.3,<5
Requires-Dist: feedendum>=0.4.0,<1
Requires-Dist: httpx>=0.28.1
Requires-Dist: lxml>=5.3.0,<6
Requires-Dist: soupsieve>=2.6,<3
Requires-Dist: tqdm>=4.67.1
Project-URL: Repository, https://github.com/timendum/raiplaysound
